xccy/__init__.py
xccy/account.py
xccy/backend.py
xccy/client.py
xccy/constants.py
xccy/exceptions.py
xccy/margin.py
xccy/oracle.py
xccy/pool.py
xccy/position.py
xccy/stream.py
xccy/tokens.py
xccy/trades.py
xccy/trading.py
xccy/types.py
xccy/abi/AprOracle.json
xccy/abi/CollateralEngine.json
xccy/abi/ERC20.json
xccy/abi/Operator.json
xccy/abi/OracleHub.json
xccy/abi/VAMMManager.json
xccy/math/__init__.py
xccy/math/fixed_point.py
xccy/math/liquidity.py
xccy/math/tick.py
xccy-0.2.2.dist-info/METADATA
xccy-0.2.2.dist-info/WHEEL
xccy-0.2.2.dist-info/RECORD
